v2_samplesheet_parser/__init__.py
v2_samplesheet_parser/functions/__init__.py
v2_samplesheet_parser/functions/parser.py
v2_samplesheet_parser/functions/retriever.py
v2_samplesheet_parser/functions/reverter.py
v2_samplesheet_parser/functions/util.py
v2_samplesheet_parser/models/__init__.py
v2_samplesheet_parser/models/base_model.py
v2_samplesheet_parser/models/bcl_convert_sections.py
v2_samplesheet_parser/models/cloud_sections.py
v2_samplesheet_parser/models/run_info_sections.py
v2_samplesheet_parser/models/samplesheet.py
v2_samplesheet_parser/models/tso500l_sections.py
v2_samplesheet_parser/models/tso500s_sections.py
v2_samplesheet_parser-0.1.0.dist-info/METADATA
v2_samplesheet_parser-0.1.0.dist-info/WHEEL
v2_samplesheet_parser-0.1.0.dist-info/licenses/LICENSE
v2_samplesheet_parser-0.1.0.dist-info/RECORD
