Metadata-Version: 2.4
Name: v2-samplesheet-parser
Version: 0.1.0
Summary: A parser for Illumina Sample Sheet v2 format
Project-URL: Home, https://github.com/umccr/v2-samplesheet-parser
Project-URL: Issue, https://github.com/umccr/v2-samplesheet-parser/issues
Author-email: Ray Liu <ray.liu@unimelb.edu.au>
License: MIT License
License-File: LICENSE
Classifier: Development Status :: 4 - Beta
Classifier: Intended Audience :: Science/Research
Classifier: License :: OSI Approved :: MIT License
Classifier: Programming Language :: Python :: 3
Classifier: Programming Language :: Python :: 3.8
Classifier: Programming Language :: Python :: 3.9
Classifier: Programming Language :: Python :: 3.10
Classifier: Programming Language :: Python :: 3.11
Classifier: Topic :: Scientific/Engineering :: Bio-Informatics
Requires-Python: >=3.8
Requires-Dist: pydantic>=2.0.0
Provides-Extra: build
Requires-Dist: build>=1.0.0; extra == 'build'
Provides-Extra: deploy
Requires-Dist: twine>=4.0.0; extra == 'deploy'
Provides-Extra: test
Requires-Dist: pytest-cov>=4.0.0; extra == 'test'
Requires-Dist: pytest>=7.0.0; extra == 'test'
